{"name":{"full":"LXXXI LICEUM OGÓLNOKSZTAŁCĄCE IM. ALEKSANDRA FREDRY","short":""},"contact":{"email":"sekretariat@fredro.edu.pl","fax":"228311454","phone":"228311454","website":"www.fredro.pl"},"students":{"type":"youth","dominantDisability":null},"location":{"street":"ul. Miła","houseNumber":"7"},"meta":{"schoolType":"Liceum ogólnokształcące","public":true,"leadingOrgan":{"name":"ŚRÓDMIEŚCIE","type":"Gmina"},"parent":"","capitalOwner":"Jednostki Samorządu Terytorialnego","establishmentDate":"1992-09-01T00:00:00","dependence":"samodzielna","regon":"15803233"}}
