{"name":{"full":"MIĘDZYNARODOWE PRYWATNE LICEUM OGÓLNOKSZTAŁCĄCE","short":""},"contact":{"email":"","fax":"","phone":"226762188","website":""},"students":{"type":"youth","dominantDisability":null},"location":{"street":"ul. Stanisława Witkiewicza","houseNumber":"16"},"meta":{"schoolType":"Liceum ogólnokształcące","public":"publicPrivileges","leadingOrgan":{"name":"Andrulewicz Monika","type":"Osoba fizyczna"},"parent":"","capitalOwner":"Krajowe Osoby Fizyczne","establishmentDate":"2005-09-01T00:00:00","dependence":"samodzielna","regon":"146464781"}}
